ika/__init__.py
ika/__version__.py
ika/abc.py
ika/chiller.py
ika/errors.py
ika/magnetic_stirrer.py
ika/overhead_stirrer.py
ika/thermoshaker.py
ika/vacuum_pump.py
ika-2.0.3.dist-info/licenses/LICENSE
ika-2.0.3.dist-info/METADATA
ika-2.0.3.dist-info/WHEEL
ika-2.0.3.dist-info/top_level.txt
ika-2.0.3.dist-info/RECORD
