Metadata-Version: 2.4
Name: ika
Version: 2.0.3
Summary: Unofficial Python package to control IKA products; not affiliated with IKA.
Home-page: https://gitlab.com/heingroup/ika
Author: Veronica Lai
Classifier: Programming Language :: Python :: 3
Requires-Python: >=3.6
License-File: LICENSE
Requires-Dist: pyserial
Dynamic: author
Dynamic: classifier
Dynamic: description
Dynamic: description-content-type
Dynamic: home-page
Dynamic: license-file
Dynamic: requires-dist
Dynamic: requires-python
Dynamic: summary
